{
  "$schema": "../card.acorn.schema.json",
  "border": "acorn",
  "name": "Tax-Exempt Status",
  "manaCost": "{1}{W}",
  "manaValue": 2,
  "colors": ["W"],
  "colorIdentity": ["W"],
  "type": "Acorn Enchantment",
  "types": ["Enchantment"],
  "supertypes": [],
  "subtypes": [],
  "text": "Spells you cast that have \"tithe,\" \"indulgence,\" or \"doom\" in their name cost {1} less to cast. We are a registered apocalypse.\nWhenever you pay life, you gain that much life instead. (We're a nonprofit. The profit is spiritual.)",
  "power": "",
  "toughness": "",
  "keywords": [],
  "rarity": "uncommon",
  "chaos": 1,
  "flavorText": "The auditors came to investigate the cult. They left as members.",
  "art": "",
  "artist": "AI Generated",
  "set": "CHAOS",
  "number": "F109"
}
