{
  "$schema": "../card.acorn.schema.json",
  "border": "acorn",
  "artPrompt": "An evocative scene of a folding-chair meeting room where a long table is ringed by far too many empty chairs and only a sparse handful of seated townsfolk, an unseen rule hanging in the air as a soft golden glow tilts the whole room toward emptiness. Dust motes drift, a gavel rests beside a forgotten casserole, the absurd stalled vote made visible. Leafy green and ivory light, composed wide in a 4:3 landscape frame, rendered as a vibrant gouache storybook illustration — saturated matte color, simplified flat-ish shapes, soft painterly edges, decorative.",
  "name": "The Quorum That Isn't",
  "manaCost": "{2}{W}",
  "manaValue": 3,
  "colors": ["W"],
  "colorIdentity": ["G", "W"],
  "type": "Enchantment",
  "types": ["Enchantment"],
  "supertypes": [],
  "subtypes": [],
  "text": "A vote at this table now requires a quorum: it counts only if the number of people physically in the room is greater than the number of empty chairs. Otherwise the motion is tabled until your next snack.\nWhile in effect, whenever a vote is tabled, you create a 1/1 green and white Voter creature token, because procedure produces volunteers the way puddles produce mosquitoes.",
  "power": "",
  "toughness": "",
  "keywords": [],
  "rarity": "rare",
  "flavorText": "Robert's Rules, footnote 12, subsection 'gotcha.'",
  "art": "",
  "artist": "AI Generated",
  "set": "CHAOS",
  "chaos": 4,
  "number": "D404",
  "extras": {
    "fourthWall": "counts people and empty chairs in the room",
    "timingGag": "tabled until your next snack"
  }
}
