{
  "$schema": "../card.acorn.schema.json",
  "border": "acorn",
  "artPrompt": "A grinning human carny in a grimy striped jacket yanks a great spinning ride-lever, the tilt-a-whirl carts whirling in a hot gold blur behind him while he counts a fistful of glinting treasure coins, ember sparks streaking past under sickly neon. Arms not insured, he beams at the viewer. The carny anchors the lower frame, the spinning ride arcing up the wide landscape frame. Wide 4:3 landscape, Rakdos red and smoky black, sinister festivity, rendered as a vibrant gouache storybook illustration — saturated matte color, simplified flat-ish shapes, soft painterly edges, decorative.",
  "name": "Tilt-a-Whirl Tactician",
  "manaCost": "{1}{B}",
  "manaValue": 2,
  "colors": ["B"],
  "colorIdentity": ["B", "R"],
  "type": "Creature — Human Carny",
  "types": ["Creature"],
  "supertypes": [],
  "subtypes": ["Human", "Carny"],
  "text": "When Tilt-a-Whirl Tactician enters the battlefield, each opponent loses 1 life for each Treasure you control, to a maximum of 3. The ride spins faster the more tickets you've sold.",
  "power": "2",
  "toughness": "2",
  "keywords": [],
  "rarity": "uncommon",
  "chaos": 2,
  "flavorText": "\"Keep your arms inside the cart. We are not insured for arms. Or carts.\"",
  "art": "",
  "artist": "AI Generated",
  "set": "CHAOS",
  "number": "C220"
}
